setup.py
dragomen/__init__.py
dragomen/client.py
dragomen/constants.py
dragomen/gtoken.py
dragomen/models.py
dragomen/urls.py
dragomen/utils.py
dragomen.egg-info/PKG-INFO
dragomen.egg-info/SOURCES.txt
dragomen.egg-info/dependency_links.txt
dragomen.egg-info/requires.txt
dragomen.egg-info/top_level.txt