Metadata-Version: 1.2
Name: dragomen
Version: 0.1
Summary: This is translation Module
Home-page: https://github.com/sumitkhamar22/dragomen
Author: Sumit
Author-email: sumitkhamar21@gmail.com
License: MIT
Download-URL: https://github.com/sumitkhamar22/dragomen/archive/0.1.tar.gz
Keywords: google translate translator
Platform: UNKNOWN
Classifier: Development Status :: 5 - Production/Stable
Classifier: Intended Audience :: Education
Classifier: Intended Audience :: End Users/Desktop
Classifier: License :: Freeware
Classifier: Operating System :: POSIX
Classifier: Operating System :: Microsoft :: Windows
Classifier: Operating System :: MacOS :: MacOS X
Classifier: Topic :: Education
Classifier: Programming Language :: Python
Classifier: Programming Language :: Python :: 3.6
Classifier: Programming Language :: Python :: 3.7
Classifier: Programming Language :: Python :: 3.8
Requires-Python: >=3.6
